font_hanken_grotesk/__init__.py
font_hanken_grotesk/files/HankenGrotesk-Bold.otf
font_hanken_grotesk/files/HankenGrotesk-BoldItalic.otf
font_hanken_grotesk/files/HankenGrotesk-Italic.otf
font_hanken_grotesk/files/HankenGrotesk-Light.otf
font_hanken_grotesk/files/HankenGrotesk-LightItalic.otf
font_hanken_grotesk/files/HankenGrotesk-Medium.otf
font_hanken_grotesk/files/HankenGrotesk-MediumItalic.otf
font_hanken_grotesk/files/HankenGrotesk-Regular.otf
font_hanken_grotesk/files/HankenGrotesk-SemiBold.otf
font_hanken_grotesk/files/HankenGrotesk-SemiBoldItalic.otf
font_hanken_grotesk/files/OFL.txt
font_hanken_grotesk-0.0.2.dist-info/DESCRIPTION.rst
font_hanken_grotesk-0.0.2.dist-info/METADATA
font_hanken_grotesk-0.0.2.dist-info/RECORD
font_hanken_grotesk-0.0.2.dist-info/WHEEL
font_hanken_grotesk-0.0.2.dist-info/entry_points.txt
font_hanken_grotesk-0.0.2.dist-info/metadata.json
font_hanken_grotesk-0.0.2.dist-info/top_level.txt
